impcache/__init__.py
impcache/exceptions.py
impcache/py.typed
impcache/repository.py
impcache/service.py
impcache/tools.py
impcache-1.0.2.dist-info/METADATA
impcache-1.0.2.dist-info/WHEEL
impcache-1.0.2.dist-info/licenses/LICENSE
impcache-1.0.2.dist-info/RECORD
