Metadata-Version: 2.1
Name: impcache
Version: 1.0.2
Summary: Simple async cache with high performance. Easy to use & ready for production.
Project-URL: Homepage, https://github.com/impsite/impcache
Project-URL: Documentation, https://github.com/impsite/impcache
Project-URL: Bug Tracker, https://github.com/impsite/impcache/issues
Author-email: Andrew Timonin <timonin.andrew@gmail.com>
License-Expression: MIT
License-File: LICENSE
Keywords: asyncio,cache,cachemanager,redis
Classifier: Framework :: AsyncIO
Classifier: Intended Audience :: Developers
Classifier: Intended Audience :: Information Technology
Classifier: Intended Audience :: System Administrators
Classifier: License :: OSI Approved :: MIT License
Classifier: Operating System :: OS Independent
Classifier: Programming Language :: Python :: 3
Classifier: Programming Language :: Python :: 3.11
Classifier: Topic :: Internet
Classifier: Topic :: Software Development
Classifier: Topic :: Software Development :: Libraries
Classifier: Topic :: Software Development :: Libraries :: Python Modules
Classifier: Typing :: Typed
Requires-Python: >=3.11
Requires-Dist: orjson>=3.8.3
Requires-Dist: redis[hiredis]>=4.4.0
